[
    {
        "image": "https://m.media-amazon.com/images/I/61sXu2HRobL.jpg",
        "caption": "Women's clothing"
    },
    {
        "image": "https://m.media-amazon.com/images/I/91U0eiMRWKL._UY695_.jpg",
        "caption": "Footwear+Handbags"
    },
    {
        "image": "https://m.media-amazon.com/images/I/51CiDHRvhAL.jpg",
        "caption": "Watches"
    },
    {
        "image": "https://m.media-amazon.com/images/I/71q6Qo2ALyL._UY695_.jpg",
        "caption": "Fashion jewellery"
    }
]